lib/__init__.py
mcp_polarion-0.1.0.dist-info/licenses/LICENSE
mcp_server/__init__.py
mcp_server/__main__.py
mcp_server/http_server.py
mcp_server/server.py
mcp_polarion-0.1.0.dist-info/METADATA
mcp_polarion-0.1.0.dist-info/WHEEL
mcp_polarion-0.1.0.dist-info/entry_points.txt
mcp_polarion-0.1.0.dist-info/top_level.txt
mcp_polarion-0.1.0.dist-info/RECORD
