Metadata-Version: 2.4
Name: mcp-polarion
Version: 0.1.0
Summary: A Model Context Protocol server for providing read-only access to Polarion ALM.
Author-email: Mounir Merah <mounir.mohammedimerah@gmail.com>
License-Expression: MIT
Project-URL: Homepage, https://github.com/mmerah/PolarionMcp
Project-URL: Bug Tracker, https://github.com/mmerah/PolarionMcp/issues
Keywords: polarion,mcp,llm,automation,testing
Classifier: Development Status :: 4 - Beta
Classifier: Intended Audience :: Developers
Classifier: Programming Language :: Python :: 3
Classifier: Programming Language :: Python :: 3.10
Classifier: Programming Language :: Python :: 3.11
Classifier: Programming Language :: Python :: 3.12
Requires-Python: >=3.10
License-File: LICENSE
Requires-Dist: pydantic>=2.0.0
Requires-Dist: polarion>=1.0.0
Requires-Dist: mcp>=1.2.0
Requires-Dist: python-dotenv>=1.0.0
Requires-Dist: fastapi>=0.104.0
Requires-Dist: uvicorn[standard]>=0.24.0
Provides-Extra: dev
Requires-Dist: black>=23.9.0; extra == "dev"
Requires-Dist: isort>=5.12.0; extra == "dev"
Requires-Dist: flake8>=6.1.0; extra == "dev"
Requires-Dist: mypy>=1.5.0; extra == "dev"
Requires-Dist: pre-commit>=3.4.0; extra == "dev"
Requires-Dist: pytest>=7.4.0; extra == "dev"
Requires-Dist: pytest-cov>=4.1.0; extra == "dev"
Requires-Dist: pytest-asyncio>=1.0.0; extra == "dev"
Provides-Extra: http
Requires-Dist: fastapi>=0.104.0; extra == "http"
Requires-Dist: uvicorn[standard]>=0.24.0; extra == "http"
Dynamic: license-file
